LICENSE
MANIFEST.in
README.rst
setup.py
bin/ygglatency
ygglatency/__init__.py
ygglatency/ygglatency.py
ygglatency.egg-info/PKG-INFO
ygglatency.egg-info/SOURCES.txt
ygglatency.egg-info/dependency_links.txt
ygglatency.egg-info/not-zip-safe
ygglatency.egg-info/requires.txt
ygglatency.egg-info/top_level.txt